{
  "legislative_session": "136",
  "identifier": "SB 244",
  "title": "Designate Abbey Gate Remembrance Day",
  "from_organization": "~{\"classification\": \"upper\"}",
  "classification": [
    "bill"
  ],
  "subject": [
    "Special Designations"
  ],
  "abstracts": [
    {
      "note": "long title",
      "abstract": "To enact section 5.63 of the Revised Code to designate August 26th as \"Abbey Gate Remembrance Day.\""
    }
  ],
  "other_titles": [
    {
      "note": "long title",
      "title": "To enact section 5.63 of the Revised Code to designate August 26th as \"Abbey Gate Remembrance Day.\""
    },
    {
      "note": "long title",
      "title": "To enact section 5.63 of the Revised Code to designate August 26th as \"Abbey Gate Remembrance Day.\""
    },
    {
      "note": "long title",
      "title": "To enact section 5.63 of the Revised Code to designate August 26th as \"Abbey Gate Remembrance Day.\""
    },
    {
      "note": "long title",
      "title": "To enact section 5.63 of the Revised Code to designate August 26th as \"Abbey Gate Remembrance Day.\""
    },
    {
      "note": "long title",
      "title": "To enact section 5.63 of the Revised Code to designate August 26th as \"Abbey Gate Remembrance Day.\""
    },
    {
      "note": "long title",
      "title": "To enact section 5.63 of the Revised Code to designate August 26th as \"Abbey Gate Remembrance Day.\""
    }
  ],
  "other_identifiers": [
    {
      "identifier": "ocd-bill-oh-136-sb244"
    }
  ],
  "actions": [
    {
      "description": "Introduced",
      "date": "2025-08-19T04:00:00+00:00",
      "organization_id": "~{\"classification\": \"upper\"}",
      "classification": [
        "introduction"
      ],
      "related_entities": [],
      "_processing": {
        "log_file_created": "2026-07-13T06:06:25Z"
      }
    },
    {
      "description": "Referred to committee",
      "date": "2025-10-01T04:00:00+00:00",
      "organization_id": "~{\"classification\": \"upper\"}",
      "classification": [
        "referral-committee"
      ],
      "related_entities": [
        {
          "name": "Senate Armed Services, Veterans Affairs and Public Safety Committee",
          "entity_type": "organization",
          "organization_id": null
        }
      ],
      "_processing": {
        "log_file_created": "2026-07-13T06:06:25Z"
      }
    },
    {
      "description": "Reported",
      "date": "2025-11-04T05:00:00+00:00",
      "organization_id": "~{\"classification\": \"upper\"}",
      "classification": [],
      "related_entities": [
        {
          "name": "Senate Armed Services, Veterans Affairs and Public Safety Committee",
          "entity_type": "organization",
          "organization_id": null
        }
      ],
      "_processing": {
        "log_file_created": "2026-07-13T06:06:25Z"
      }
    },
    {
      "description": "Passed",
      "date": "2025-11-05T05:00:00+00:00",
      "organization_id": "~{\"classification\": \"upper\"}",
      "classification": [
        "passage"
      ],
      "related_entities": [],
      "_processing": {
        "log_file_created": "2026-07-13T06:06:25Z"
      }
    },
    {
      "description": "Introduced",
      "date": "2025-11-10T05:00:00+00:00",
      "organization_id": "~{\"classification\": \"lower\"}",
      "classification": [
        "introduction"
      ],
      "related_entities": [],
      "_processing": {
        "log_file_created": "2026-07-13T06:06:25Z"
      }
    },
    {
      "description": "Referred to committee",
      "date": "2025-11-12T05:00:00+00:00",
      "organization_id": "~{\"classification\": \"lower\"}",
      "classification": [
        "referral-committee"
      ],
      "related_entities": [
        {
          "name": "House Veterans and Military Development Committee",
          "entity_type": "organization",
          "organization_id": null
        }
      ],
      "_processing": {
        "log_file_created": "2026-07-13T06:06:25Z"
      }
    },
    {
      "description": "Reported - Amended",
      "date": "2026-02-25T05:00:00+00:00",
      "organization_id": "~{\"classification\": \"lower\"}",
      "classification": [],
      "related_entities": [
        {
          "name": "House Veterans and Military Development Committee",
          "entity_type": "organization",
          "organization_id": null
        }
      ],
      "_processing": {
        "log_file_created": "2026-07-14T12:59:50Z"
      }
    },
    {
      "description": "Passed",
      "date": "2026-03-04T05:00:00+00:00",
      "organization_id": "~{\"classification\": \"lower\"}",
      "classification": [
        "passage"
      ],
      "related_entities": [],
      "_processing": {
        "log_file_created": "2026-07-14T12:59:50Z"
      }
    },
    {
      "description": "Concurred in House amendments",
      "date": "2026-03-25T04:00:00+00:00",
      "organization_id": "~{\"classification\": \"upper\"}",
      "classification": [
        "amendment-passage"
      ],
      "related_entities": [],
      "_processing": {
        "log_file_created": "2026-07-14T12:59:50Z"
      }
    },
    {
      "description": "Sent To The Governor",
      "date": "2026-03-26T04:00:00+00:00",
      "organization_id": "~{\"classification\": \"legislature\"}",
      "classification": [
        "passage"
      ],
      "related_entities": [],
      "_processing": {
        "log_file_created": "2026-07-14T12:59:50Z"
      }
    },
    {
      "description": "Signed By The Governor",
      "date": "2026-03-31T04:00:00+00:00",
      "organization_id": "~{\"classification\": \"legislature\"}",
      "classification": [
        "became-law"
      ],
      "related_entities": [],
      "_processing": {
        "log_file_created": "2026-07-14T12:59:50Z"
      }
    },
    {
      "description": "Effective",
      "date": "2026-06-30T04:00:00+00:00",
      "organization_id": "~{\"classification\": \"legislature\"}",
      "classification": [
        "became-law"
      ],
      "related_entities": [],
      "_processing": {
        "log_file_created": "2026-07-14T12:59:50Z"
      }
    },
    {
      "description": "Effective 6/30/26",
      "date": "2026-06-30T04:00:00+00:00",
      "organization_id": "~{\"classification\": \"executive\"}",
      "classification": [
        "became-law"
      ],
      "related_entities": [],
      "_processing": {
        "log_file_created": "2026-07-14T12:59:50Z"
      }
    }
  ],
  "sponsorships": [
    {
      "name": "Kristina D. Roegner",
      "classification": "primary",
      "entity_type": "person",
      "primary": true,
      "person_id": "~{\"name\": \"Kristina D. Roegner\"}",
      "organization_id": null
    },
    {
      "name": "Jane M. Timken",
      "classification": "primary",
      "entity_type": "person",
      "primary": true,
      "person_id": "~{\"name\": \"Jane M. Timken\"}",
      "organization_id": null
    }
  ],
  "related_bills": [],
  "versions": [
    {
      "note": "As Introduced",
      "links": [
        {
          "url": "https://search-prod.lis.state.oh.us/api/v2/general_assembly_136/legislation/sb244/00_IN/pdf/",
          "media_type": "application/pdf"
        },
        {
          "url": "https://search-prod.lis.state.oh.us/api/v2/general_assembly_136/legislation/sb244/00_IN/html/",
          "media_type": "text/html"
        }
      ],
      "date": "",
      "classification": ""
    },
    {
      "note": "As Reported by the Senate Armed Services, Veterans Affairs and Public Safety Committee",
      "links": [
        {
          "url": "https://search-prod.lis.state.oh.us/api/v2/general_assembly_136/legislation/sb244/01_RS/pdf/",
          "media_type": "application/pdf"
        },
        {
          "url": "https://search-prod.lis.state.oh.us/api/v2/general_assembly_136/legislation/sb244/01_RS/html/",
          "media_type": "text/html"
        }
      ],
      "date": "",
      "classification": ""
    },
    {
      "note": "As Passed by the Senate",
      "links": [
        {
          "url": "https://search-prod.lis.state.oh.us/api/v2/general_assembly_136/legislation/sb244/02_PS/pdf/",
          "media_type": "application/pdf"
        },
        {
          "url": "https://search-prod.lis.state.oh.us/api/v2/general_assembly_136/legislation/sb244/02_PS/html/",
          "media_type": "text/html"
        }
      ],
      "date": "",
      "classification": ""
    },
    {
      "note": "As Reported by the House Veterans and Military Development Committee",
      "links": [
        {
          "url": "https://search-prod.lis.state.oh.us/api/v2/general_assembly_136/legislation/sb244/03_RH/pdf/",
          "media_type": "application/pdf"
        },
        {
          "url": "https://search-prod.lis.state.oh.us/api/v2/general_assembly_136/legislation/sb244/03_RH/html/",
          "media_type": "text/html"
        }
      ],
      "date": "",
      "classification": ""
    },
    {
      "note": "As Passed by the House",
      "links": [
        {
          "url": "https://search-prod.lis.state.oh.us/api/v2/general_assembly_136/legislation/sb244/04_PH/pdf/",
          "media_type": "application/pdf"
        },
        {
          "url": "https://search-prod.lis.state.oh.us/api/v2/general_assembly_136/legislation/sb244/04_PH/html/",
          "media_type": "text/html"
        }
      ],
      "date": "",
      "classification": ""
    },
    {
      "note": "As Enrolled",
      "links": [
        {
          "url": "https://search-prod.lis.state.oh.us/api/v2/general_assembly_136/legislation/sb244/05_EN/pdf/",
          "media_type": "application/pdf"
        },
        {
          "url": "https://search-prod.lis.state.oh.us/api/v2/general_assembly_136/legislation/sb244/05_EN/html/",
          "media_type": "text/html"
        }
      ],
      "date": "",
      "classification": ""
    }
  ],
  "documents": [
    {
      "note": "Analysis: Final Analysis",
      "links": [
        {
          "url": "https://www.legislature.ohio.gov//download?key=27753",
          "media_type": "application/pdf"
        }
      ],
      "date": "",
      "classification": ""
    },
    {
      "note": "Analysis: As Reported By House Committee",
      "links": [
        {
          "url": "https://www.legislature.ohio.gov//download?key=27212",
          "media_type": "application/pdf"
        }
      ],
      "date": "",
      "classification": ""
    },
    {
      "note": "Analysis: As Passed By Senate",
      "links": [
        {
          "url": "https://www.legislature.ohio.gov//download?key=26652",
          "media_type": "application/pdf"
        }
      ],
      "date": "",
      "classification": ""
    },
    {
      "note": "Analysis: As Reported By Senate Committee",
      "links": [
        {
          "url": "https://www.legislature.ohio.gov//download?key=26479",
          "media_type": "application/pdf"
        }
      ],
      "date": "",
      "classification": ""
    },
    {
      "note": "Analysis: As Introduced",
      "links": [
        {
          "url": "https://www.legislature.ohio.gov//download?key=26185",
          "media_type": "application/pdf"
        }
      ],
      "date": "",
      "classification": ""
    },
    {
      "note": "Fiscal Notes: As Passed By House",
      "links": [
        {
          "url": "https://www.legislature.ohio.gov//download?key=27334",
          "media_type": "application/pdf"
        }
      ],
      "date": "",
      "classification": ""
    },
    {
      "note": "Fiscal Notes: As Reported By House Committee",
      "links": [
        {
          "url": "https://www.legislature.ohio.gov//download?key=27217",
          "media_type": "application/pdf"
        }
      ],
      "date": "",
      "classification": ""
    },
    {
      "note": "Fiscal Notes: As Passed By Senate",
      "links": [
        {
          "url": "https://www.legislature.ohio.gov//download?key=26504",
          "media_type": "application/pdf"
        }
      ],
      "date": "",
      "classification": ""
    },
    {
      "note": "Fiscal Notes: As Reported By Senate Committee",
      "links": [
        {
          "url": "https://www.legislature.ohio.gov//download?key=26395",
          "media_type": "application/pdf"
        }
      ],
      "date": "",
      "classification": ""
    },
    {
      "note": "Fiscal Notes: As Introduced",
      "links": [
        {
          "url": "https://www.legislature.ohio.gov//download?key=26299",
          "media_type": "application/pdf"
        }
      ],
      "date": "",
      "classification": ""
    },
    {
      "note": "Additional Documents: Synopsis of House Committee Amendments",
      "links": [
        {
          "url": "https://www.legislature.ohio.gov//download?key=27213",
          "media_type": "application/pdf"
        }
      ],
      "date": "",
      "classification": ""
    }
  ],
  "citations": [],
  "sources": [
    {
      "url": "https://www.legislature.ohio.gov/legislation/136/sb244",
      "note": ""
    },
    {
      "url": "https://search-prod.lis.state.oh.us/api/v2/general_assembly_136/legislation/sb244/",
      "note": ""
    },
    {
      "url": "https://search-prod.lis.state.oh.us/api/v2/general_assembly_136/legislation/sb244/",
      "note": ""
    },
    {
      "url": "https://search-prod.lis.state.oh.us/api/v2/general_assembly_136/legislation/sb244/",
      "note": ""
    },
    {
      "url": "https://search-prod.lis.state.oh.us/api/v2/general_assembly_136/legislation/sb244/",
      "note": ""
    },
    {
      "url": "https://search-prod.lis.state.oh.us/api/v2/general_assembly_136/legislation/sb244/",
      "note": ""
    },
    {
      "url": "https://search-prod.lis.state.oh.us/api/v2/general_assembly_136/legislation/sb244/",
      "note": ""
    }
  ],
  "extras": {},
  "jurisdiction": {
    "id": "ocd-jurisdiction/country:us/state:oh/government",
    "name": "Ohio",
    "classification": "state",
    "division_id": "ocd-division/country:us/state:oh"
  },
  "_processing": {
    "logs_latest_update": "2026-07-14T12:59:50Z",
    "text_extraction_latest_update": "2026-07-14T21:04:43.326145Z"
  }
}