{
  "legislative_session": "136",
  "identifier": "SB 352",
  "title": "Regards behavioral health screenings in the perinatal period",
  "from_organization": "~{\"classification\": \"upper\"}",
  "classification": [
    "bill"
  ],
  "subject": [
    "Commerce",
    "Health Care",
    "Health and Human Services",
    "Insurance"
  ],
  "abstracts": [
    {
      "note": "long title",
      "abstract": "To enact sections 3702.41, 3902.65, and 5119.171 of the Revised Code regarding behavioral health screenings in the perinatal period and to make an appropriation."
    }
  ],
  "other_titles": [
    {
      "note": "long title",
      "title": "To enact sections 3702.41, 3902.65, and 5119.171 of the Revised Code regarding behavioral health screenings in the perinatal period and to make an appropriation."
    }
  ],
  "other_identifiers": [
    {
      "identifier": "ocd-bill-oh-136-sb352"
    }
  ],
  "actions": [
    {
      "description": "Introduced",
      "date": "2026-02-10T05:00:00+00:00",
      "organization_id": "~{\"classification\": \"upper\"}",
      "classification": [
        "introduction"
      ],
      "related_entities": [],
      "_processing": {
        "log_file_created": "2026-07-14T12:59:50Z"
      }
    },
    {
      "description": "Referred to committee",
      "date": "2026-02-11T05:00:00+00:00",
      "organization_id": "~{\"classification\": \"upper\"}",
      "classification": [
        "referral-committee"
      ],
      "related_entities": [
        {
          "name": "Senate Finance Committee",
          "entity_type": "organization",
          "organization_id": null
        }
      ],
      "_processing": {
        "log_file_created": "2026-07-14T12:59:50Z"
      }
    }
  ],
  "sponsorships": [
    {
      "name": "Casey Weinstein",
      "classification": "primary",
      "entity_type": "person",
      "primary": true,
      "person_id": "~{\"name\": \"Casey Weinstein\"}",
      "organization_id": null
    },
    {
      "name": "Jane M. Timken",
      "classification": "primary",
      "entity_type": "person",
      "primary": true,
      "person_id": "~{\"name\": \"Jane M. Timken\"}",
      "organization_id": null
    }
  ],
  "related_bills": [],
  "versions": [
    {
      "note": "As Introduced",
      "links": [
        {
          "url": "https://search-prod.lis.state.oh.us/api/v2/general_assembly_136/legislation/sb352/00_IN/pdf/",
          "media_type": "application/pdf"
        },
        {
          "url": "https://search-prod.lis.state.oh.us/api/v2/general_assembly_136/legislation/sb352/00_IN/html/",
          "media_type": "text/html"
        }
      ],
      "date": "",
      "classification": ""
    }
  ],
  "documents": [
    {
      "note": "Analysis: As Introduced",
      "links": [
        {
          "url": "https://www.legislature.ohio.gov//download?key=27240",
          "media_type": "application/pdf"
        }
      ],
      "date": "",
      "classification": ""
    },
    {
      "note": "Fiscal Notes: As Introduced",
      "links": [
        {
          "url": "https://www.legislature.ohio.gov//download?key=27315",
          "media_type": "application/pdf"
        }
      ],
      "date": "",
      "classification": ""
    }
  ],
  "citations": [],
  "sources": [
    {
      "url": "https://www.legislature.ohio.gov/legislation/136/sb352",
      "note": ""
    },
    {
      "url": "https://search-prod.lis.state.oh.us/api/v2/general_assembly_136/legislation/sb352/",
      "note": ""
    }
  ],
  "extras": {},
  "jurisdiction": {
    "id": "ocd-jurisdiction/country:us/state:oh/government",
    "name": "Ohio",
    "classification": "state",
    "division_id": "ocd-division/country:us/state:oh"
  },
  "_processing": {
    "logs_latest_update": "2026-07-14T12:59:50Z",
    "text_extraction_latest_update": "2026-07-14T20:46:53.431902Z"
  }
}