{
  "identifier": "",
  "motion_text": "Reported",
  "motion_classification": [
    "amendment",
    "committee-passage"
  ],
  "start_date": "2025-11-05T21:02:12+00:00",
  "result": "fail",
  "organization": "~{\"classification\": \"upper\"}",
  "legislative_session": "136",
  "bill": "6a761f4e-7dc8-11f1-9627-ca0073f565ed",
  "bill_action": null,
  "bill_identifier": "SB 293",
  "votes": [
    {
      "option": "yes",
      "voter_name": "Kristina D. Roegner",
      "voter_id": "~{\"name\": \"Kristina D. Roegner\"}",
      "note": ""
    },
    {
      "option": "yes",
      "voter_name": "Theresa Gavarone",
      "voter_id": "~{\"name\": \"Theresa Gavarone\"}",
      "note": ""
    },
    {
      "option": "yes",
      "voter_name": "Stephen A. Huffman",
      "voter_id": "~{\"name\": \"Stephen A. Huffman\"}",
      "note": ""
    },
    {
      "option": "yes",
      "voter_name": "Bill Reineke",
      "voter_id": "~{\"name\": \"Bill Reineke\"}",
      "note": ""
    },
    {
      "option": "yes",
      "voter_name": "Jane M. Timken",
      "voter_id": "~{\"name\": \"Jane M. Timken\"}",
      "note": ""
    },
    {
      "option": "no",
      "voter_name": "Willis E. Blackshear, Jr.",
      "voter_id": "~{\"name\": \"Willis E. Blackshear, Jr.\"}",
      "note": ""
    },
    {
      "option": "no",
      "voter_name": "William P. DeMora",
      "voter_id": "~{\"name\": \"William P. DeMora\"}",
      "note": ""
    }
  ],
  "counts": [
    {
      "option": "yes",
      "value": 5
    },
    {
      "option": "no",
      "value": 2
    }
  ],
  "sources": [
    {
      "url": "https://search-prod.lis.state.oh.us/api/v2/general_assembly_136/legislation/sb293/actions",
      "note": ""
    }
  ],
  "extras": {},
  "dedupe_key": "vote-revno-868943"
}