{
  "legislative_session": "136",
  "identifier": "HB 91",
  "title": "Establish Traumatic Brain Injury Treatment Accelerator Program",
  "from_organization": "~{\"classification\": \"lower\"}",
  "classification": [
    "bill"
  ],
  "subject": [
    "Education",
    "Finance and Appropriations",
    "Health Care",
    "Health and Human Services",
    "Higher Education"
  ],
  "abstracts": [
    {
      "note": "long title",
      "abstract": "To enact section 3333.802 of the Revised Code to establish the Traumatic Brain Injury Treatment Accelerator Program and to make an appropriation."
    }
  ],
  "other_titles": [
    {
      "note": "long title",
      "title": "To enact section 3333.802 of the Revised Code to establish the Traumatic Brain Injury Treatment Accelerator Program and to make an appropriation."
    }
  ],
  "other_identifiers": [
    {
      "identifier": "ocd-bill-oh-136-hb91"
    }
  ],
  "actions": [
    {
      "description": "Introduced",
      "date": "2025-02-11T05:00:00+00:00",
      "organization_id": "~{\"classification\": \"lower\"}",
      "classification": [
        "introduction"
      ],
      "related_entities": [],
      "_processing": {
        "log_file_created": "2026-07-13T06:06:24Z"
      }
    },
    {
      "description": "Referred to committee",
      "date": "2025-02-12T05:00:00+00:00",
      "organization_id": "~{\"classification\": \"lower\"}",
      "classification": [
        "referral-committee"
      ],
      "related_entities": [
        {
          "name": "House Workforce and Higher Education Committee",
          "entity_type": "organization",
          "organization_id": null
        }
      ],
      "_processing": {
        "log_file_created": "2026-07-13T06:06:24Z"
      }
    }
  ],
  "sponsorships": [
    {
      "name": "Mike Odioso",
      "classification": "primary",
      "entity_type": "person",
      "primary": true,
      "person_id": "~{\"name\": \"Mike Odioso\"}",
      "organization_id": null
    },
    {
      "name": "Kellie Deeter",
      "classification": "primary",
      "entity_type": "person",
      "primary": true,
      "person_id": "~{\"name\": \"Kellie Deeter\"}",
      "organization_id": null
    },
    {
      "name": "Sean P. Brennan",
      "classification": "cosponsor",
      "entity_type": "person",
      "primary": false,
      "person_id": "~{\"name\": \"Sean P. Brennan\"}",
      "organization_id": null
    },
    {
      "name": "Karen Brownlee",
      "classification": "cosponsor",
      "entity_type": "person",
      "primary": false,
      "person_id": "~{\"name\": \"Karen Brownlee\"}",
      "organization_id": null
    },
    {
      "name": "Michael D. Dovilla",
      "classification": "cosponsor",
      "entity_type": "person",
      "primary": false,
      "person_id": "~{\"name\": \"Michael D. Dovilla\"}",
      "organization_id": null
    },
    {
      "name": "Monica Robb Blasdel",
      "classification": "cosponsor",
      "entity_type": "person",
      "primary": false,
      "person_id": "~{\"name\": \"Monica Robb Blasdel\"}",
      "organization_id": null
    },
    {
      "name": "Mark Sigrist",
      "classification": "cosponsor",
      "entity_type": "person",
      "primary": false,
      "person_id": "~{\"name\": \"Mark Sigrist\"}",
      "organization_id": null
    },
    {
      "name": "Bride Rose Sweeney",
      "classification": "cosponsor",
      "entity_type": "person",
      "primary": false,
      "person_id": "~{\"name\": \"Bride Rose Sweeney\"}",
      "organization_id": null
    },
    {
      "name": "Eric Synenberg",
      "classification": "cosponsor",
      "entity_type": "person",
      "primary": false,
      "person_id": "~{\"name\": \"Eric Synenberg\"}",
      "organization_id": null
    },
    {
      "name": "Josh Williams",
      "classification": "cosponsor",
      "entity_type": "person",
      "primary": false,
      "person_id": "~{\"name\": \"Josh Williams\"}",
      "organization_id": null
    }
  ],
  "related_bills": [],
  "versions": [
    {
      "note": "As Introduced",
      "links": [
        {
          "url": "https://search-prod.lis.state.oh.us/api/v2/general_assembly_136/legislation/hb91/00_IN/pdf/",
          "media_type": "application/pdf"
        },
        {
          "url": "https://search-prod.lis.state.oh.us/api/v2/general_assembly_136/legislation/hb91/00_IN/html/",
          "media_type": "text/html"
        }
      ],
      "date": "",
      "classification": ""
    }
  ],
  "documents": [
    {
      "note": "Analysis: As Introduced",
      "links": [
        {
          "url": "https://www.legislature.ohio.gov//download?key=25092",
          "media_type": "application/pdf"
        }
      ],
      "date": "",
      "classification": ""
    },
    {
      "note": "Fiscal Notes: As Introduced",
      "links": [
        {
          "url": "https://www.legislature.ohio.gov//download?key=25229",
          "media_type": "application/pdf"
        }
      ],
      "date": "",
      "classification": ""
    }
  ],
  "citations": [],
  "sources": [
    {
      "url": "https://www.legislature.ohio.gov/legislation/136/hb91",
      "note": ""
    },
    {
      "url": "https://search-prod.lis.state.oh.us/api/v2/general_assembly_136/legislation/hb91/",
      "note": ""
    }
  ],
  "extras": {},
  "jurisdiction": {
    "id": "ocd-jurisdiction/country:us/state:oh/government",
    "name": "Ohio",
    "classification": "state",
    "division_id": "ocd-division/country:us/state:oh"
  },
  "_processing": {
    "logs_latest_update": "2026-07-13T06:06:24Z"
  }
}