{
  "identifier": "",
  "motion_text": "Reported",
  "motion_classification": [
    "amendment",
    "committee-passage"
  ],
  "start_date": "2026-05-20T20:56:30+00:00",
  "result": "fail",
  "organization": "~{\"classification\": \"lower\"}",
  "legislative_session": "136",
  "bill": "1ec0216c-7f7b-11f1-8c68-6e40a564de15",
  "bill_action": null,
  "bill_identifier": "HB 163",
  "votes": [
    {
      "option": "yes",
      "voter_name": "Roy Klopfenstein",
      "voter_id": "~{\"name\": \"Roy Klopfenstein\"}",
      "note": ""
    },
    {
      "option": "yes",
      "voter_name": "Johnathan Newman",
      "voter_id": "~{\"name\": \"Johnathan Newman\"}",
      "note": ""
    },
    {
      "option": "yes",
      "voter_name": "Joseph A. Miller, III",
      "voter_id": "~{\"name\": \"Joseph A. Miller, III\"}",
      "note": ""
    },
    {
      "option": "yes",
      "voter_name": "Tim Barhorst",
      "voter_id": "~{\"name\": \"Tim Barhorst\"}",
      "note": ""
    },
    {
      "option": "yes",
      "voter_name": "Juanita O. Brent",
      "voter_id": "~{\"name\": \"Juanita O. Brent\"}",
      "note": ""
    },
    {
      "option": "yes",
      "voter_name": "Christine Cockley",
      "voter_id": "~{\"name\": \"Christine Cockley\"}",
      "note": ""
    },
    {
      "option": "yes",
      "voter_name": "Rodney Creech",
      "voter_id": "~{\"name\": \"Rodney Creech\"}",
      "note": ""
    },
    {
      "option": "yes",
      "voter_name": "Mark Hiner",
      "voter_id": "~{\"name\": \"Mark Hiner\"}",
      "note": ""
    },
    {
      "option": "yes",
      "voter_name": "Ty Moore",
      "voter_id": "~{\"name\": \"Ty Moore\"}",
      "note": ""
    },
    {
      "option": "yes",
      "voter_name": "Diane Mullins",
      "voter_id": "~{\"name\": \"Diane Mullins\"}",
      "note": ""
    },
    {
      "option": "yes",
      "voter_name": "Bob Peterson",
      "voter_id": "~{\"name\": \"Bob Peterson\"}",
      "note": ""
    },
    {
      "option": "yes",
      "voter_name": "Jean Schmidt",
      "voter_id": "~{\"name\": \"Jean Schmidt\"}",
      "note": ""
    },
    {
      "option": "yes",
      "voter_name": "Veronica R. Sims",
      "voter_id": "~{\"name\": \"Veronica R. Sims\"}",
      "note": ""
    }
  ],
  "counts": [
    {
      "option": "yes",
      "value": 13
    },
    {
      "option": "no",
      "value": 0
    }
  ],
  "sources": [
    {
      "url": "https://search-prod.lis.state.oh.us/api/v2/general_assembly_136/legislation/hb163/actions",
      "note": ""
    }
  ],
  "extras": {},
  "dedupe_key": "vote-revno-1183631"
}