{
  "legislative_session": "136",
  "identifier": "HB 743",
  "title": "Prohibit the use of intentionally added PFAS in various products",
  "from_organization": "~{\"classification\": \"lower\"}",
  "classification": [
    "bill"
  ],
  "subject": [
    "Commerce",
    "Environment and Natural Resources"
  ],
  "abstracts": [
    {
      "note": "long title",
      "abstract": "To amend section 3745.015 and to enact sections 3745.81, 3745.82, 3745.83, 3745.84, 3745.85, 3745.86, and 3745.87 of the Revised Code to prohibit, with exceptions, the use of intentionally added PFAS in various products."
    }
  ],
  "other_titles": [
    {
      "note": "long title",
      "title": "To amend section 3745.015 and to enact sections 3745.81, 3745.82, 3745.83, 3745.84, 3745.85, 3745.86, and 3745.87 of the Revised Code to prohibit, with exceptions, the use of intentionally added PFAS in various products."
    }
  ],
  "other_identifiers": [
    {
      "identifier": "ocd-bill-oh-136-hb743"
    }
  ],
  "actions": [
    {
      "description": "Introduced",
      "date": "2026-03-10T04:00:00+00:00",
      "organization_id": "~{\"classification\": \"lower\"}",
      "classification": [
        "introduction"
      ],
      "related_entities": [],
      "_processing": {
        "log_file_created": "2026-07-14T12:59:49Z"
      }
    },
    {
      "description": "Referred to committee",
      "date": "2026-03-18T04:00:00+00:00",
      "organization_id": "~{\"classification\": \"lower\"}",
      "classification": [
        "referral-committee"
      ],
      "related_entities": [
        {
          "name": "House General Government Committee",
          "entity_type": "organization",
          "organization_id": null
        }
      ],
      "_processing": {
        "log_file_created": "2026-07-14T12:59:49Z"
      }
    }
  ],
  "sponsorships": [
    {
      "name": "Daniel P. Troy",
      "classification": "primary",
      "entity_type": "person",
      "primary": true,
      "person_id": "~{\"name\": \"Daniel P. Troy\"}",
      "organization_id": null
    },
    {
      "name": "Elgin Rogers, Jr.",
      "classification": "primary",
      "entity_type": "person",
      "primary": true,
      "person_id": "~{\"name\": \"Elgin Rogers, Jr.\"}",
      "organization_id": null
    },
    {
      "name": "Sean P. Brennan",
      "classification": "cosponsor",
      "entity_type": "person",
      "primary": false,
      "person_id": "~{\"name\": \"Sean P. Brennan\"}",
      "organization_id": null
    },
    {
      "name": "Karen Brownlee",
      "classification": "cosponsor",
      "entity_type": "person",
      "primary": false,
      "person_id": "~{\"name\": \"Karen Brownlee\"}",
      "organization_id": null
    },
    {
      "name": "Crystal Lett",
      "classification": "cosponsor",
      "entity_type": "person",
      "primary": false,
      "person_id": "~{\"name\": \"Crystal Lett\"}",
      "organization_id": null
    },
    {
      "name": "Lauren McNally",
      "classification": "cosponsor",
      "entity_type": "person",
      "primary": false,
      "person_id": "~{\"name\": \"Lauren McNally\"}",
      "organization_id": null
    },
    {
      "name": "Joseph A. Miller, III",
      "classification": "cosponsor",
      "entity_type": "person",
      "primary": false,
      "person_id": "~{\"name\": \"Joseph A. Miller, III\"}",
      "organization_id": null
    },
    {
      "name": "Beryl Piccolantonio",
      "classification": "cosponsor",
      "entity_type": "person",
      "primary": false,
      "person_id": "~{\"name\": \"Beryl Piccolantonio\"}",
      "organization_id": null
    },
    {
      "name": "C. Allison Russo",
      "classification": "cosponsor",
      "entity_type": "person",
      "primary": false,
      "person_id": "~{\"name\": \"C. Allison Russo\"}",
      "organization_id": null
    },
    {
      "name": "Eric Synenberg",
      "classification": "cosponsor",
      "entity_type": "person",
      "primary": false,
      "person_id": "~{\"name\": \"Eric Synenberg\"}",
      "organization_id": null
    },
    {
      "name": "Terrence Upchurch",
      "classification": "cosponsor",
      "entity_type": "person",
      "primary": false,
      "person_id": "~{\"name\": \"Terrence Upchurch\"}",
      "organization_id": null
    }
  ],
  "related_bills": [],
  "versions": [
    {
      "note": "As Introduced",
      "links": [
        {
          "url": "https://search-prod.lis.state.oh.us/api/v2/general_assembly_136/legislation/hb743/00_IN/pdf/",
          "media_type": "application/pdf"
        },
        {
          "url": "https://search-prod.lis.state.oh.us/api/v2/general_assembly_136/legislation/hb743/00_IN/html/",
          "media_type": "text/html"
        }
      ],
      "date": "",
      "classification": ""
    }
  ],
  "documents": [],
  "citations": [],
  "sources": [
    {
      "url": "https://www.legislature.ohio.gov/legislation/136/hb743",
      "note": ""
    },
    {
      "url": "https://search-prod.lis.state.oh.us/api/v2/general_assembly_136/legislation/hb743/",
      "note": ""
    }
  ],
  "extras": {},
  "jurisdiction": {
    "id": "ocd-jurisdiction/country:us/state:oh/government",
    "name": "Ohio",
    "classification": "state",
    "division_id": "ocd-division/country:us/state:oh"
  },
  "_processing": {
    "logs_latest_update": "2026-07-14T12:59:49Z"
  }
}