{
  "legislative_session": "136",
  "identifier": "HB 748",
  "title": "Establish the Armed Forces Reserve Component Scholarship Program",
  "from_organization": "~{\"classification\": \"lower\"}",
  "classification": [
    "bill"
  ],
  "subject": [
    "Education",
    "Higher Education",
    "Military and Veterans"
  ],
  "abstracts": [
    {
      "note": "long title",
      "abstract": "To enact sections 3333.46, 3333.461, and 3333.462 of the Revised Code to establish the Armed Forces Reserve Component Scholarship Program and related funds and to make an appropriation."
    }
  ],
  "other_titles": [
    {
      "note": "long title",
      "title": "To enact sections 3333.46, 3333.461, and 3333.462 of the Revised Code to establish the Armed Forces Reserve Component Scholarship Program and related funds and to make an appropriation."
    }
  ],
  "other_identifiers": [
    {
      "identifier": "ocd-bill-oh-136-hb748"
    }
  ],
  "actions": [
    {
      "description": "Introduced",
      "date": "2026-03-10T04:00:00+00:00",
      "organization_id": "~{\"classification\": \"lower\"}",
      "classification": [
        "introduction"
      ],
      "related_entities": [],
      "_processing": {
        "log_file_created": "2026-07-14T12:59:51Z"
      }
    },
    {
      "description": "Referred to committee",
      "date": "2026-03-18T04:00:00+00:00",
      "organization_id": "~{\"classification\": \"lower\"}",
      "classification": [
        "referral-committee"
      ],
      "related_entities": [
        {
          "name": "House Workforce and Higher Education Committee",
          "entity_type": "organization",
          "organization_id": null
        }
      ],
      "_processing": {
        "log_file_created": "2026-07-14T12:59:51Z"
      }
    }
  ],
  "sponsorships": [
    {
      "name": "Bernard Willis",
      "classification": "primary",
      "entity_type": "person",
      "primary": true,
      "person_id": "~{\"name\": \"Bernard Willis\"}",
      "organization_id": null
    },
    {
      "name": "Michael D. Dovilla",
      "classification": "primary",
      "entity_type": "person",
      "primary": true,
      "person_id": "~{\"name\": \"Michael D. Dovilla\"}",
      "organization_id": null
    },
    {
      "name": "Kellie Deeter",
      "classification": "cosponsor",
      "entity_type": "person",
      "primary": false,
      "person_id": "~{\"name\": \"Kellie Deeter\"}",
      "organization_id": null
    },
    {
      "name": "Mark Johnson",
      "classification": "cosponsor",
      "entity_type": "person",
      "primary": false,
      "person_id": "~{\"name\": \"Mark Johnson\"}",
      "organization_id": null
    },
    {
      "name": "Kevin Ritter",
      "classification": "cosponsor",
      "entity_type": "person",
      "primary": false,
      "person_id": "~{\"name\": \"Kevin Ritter\"}",
      "organization_id": null
    },
    {
      "name": "Jodi Salvo",
      "classification": "cosponsor",
      "entity_type": "person",
      "primary": false,
      "person_id": "~{\"name\": \"Jodi Salvo\"}",
      "organization_id": null
    },
    {
      "name": "Josh Williams",
      "classification": "cosponsor",
      "entity_type": "person",
      "primary": false,
      "person_id": "~{\"name\": \"Josh Williams\"}",
      "organization_id": null
    }
  ],
  "related_bills": [],
  "versions": [
    {
      "note": "As Introduced",
      "links": [
        {
          "url": "https://search-prod.lis.state.oh.us/api/v2/general_assembly_136/legislation/hb748/00_IN/pdf/",
          "media_type": "application/pdf"
        },
        {
          "url": "https://search-prod.lis.state.oh.us/api/v2/general_assembly_136/legislation/hb748/00_IN/html/",
          "media_type": "text/html"
        }
      ],
      "date": "",
      "classification": ""
    }
  ],
  "documents": [
    {
      "note": "Analysis: As Introduced",
      "links": [
        {
          "url": "https://www.legislature.ohio.gov//download?key=27562",
          "media_type": "application/pdf"
        }
      ],
      "date": "",
      "classification": ""
    },
    {
      "note": "Fiscal Notes: As Pending in House Committee",
      "links": [
        {
          "url": "https://www.legislature.ohio.gov//download?key=27697",
          "media_type": "application/pdf"
        }
      ],
      "date": "",
      "classification": ""
    }
  ],
  "citations": [],
  "sources": [
    {
      "url": "https://www.legislature.ohio.gov/legislation/136/hb748",
      "note": ""
    },
    {
      "url": "https://search-prod.lis.state.oh.us/api/v2/general_assembly_136/legislation/hb748/",
      "note": ""
    }
  ],
  "extras": {},
  "jurisdiction": {
    "id": "ocd-jurisdiction/country:us/state:oh/government",
    "name": "Ohio",
    "classification": "state",
    "division_id": "ocd-division/country:us/state:oh"
  },
  "_processing": {
    "logs_latest_update": "2026-07-14T12:59:51Z"
  }
}