{
  "legislative_session": "136",
  "identifier": "HB 362",
  "title": "Regulate fraudulent synthetic media for influencing elections",
  "from_organization": "~{\"classification\": \"lower\"}",
  "classification": [
    "bill"
  ],
  "subject": [
    "Campaign Finance",
    "Civil Law",
    "Courts and Civil Law",
    "Elections"
  ],
  "abstracts": [
    {
      "note": "long title",
      "abstract": "To amend sections 3517.153, 3517.154, 3517.155, 3517.993, and 3599.40 and to enact section 3517.24 of the Revised Code to regulate the dissemination of deceptive and fraudulent synthetic media for the purpose of influencing the results of an election."
    }
  ],
  "other_titles": [
    {
      "note": "long title",
      "title": "To amend sections 3517.153, 3517.154, 3517.155, 3517.993, and 3599.40 and to enact section 3517.24 of the Revised Code to regulate the dissemination of deceptive and fraudulent synthetic media for the purpose of influencing the results of an election."
    }
  ],
  "other_identifiers": [
    {
      "identifier": "ocd-bill-oh-136-hb362"
    }
  ],
  "actions": [
    {
      "description": "Introduced",
      "date": "2025-06-12T04:00:00+00:00",
      "organization_id": "~{\"classification\": \"lower\"}",
      "classification": [
        "introduction"
      ],
      "related_entities": [],
      "_processing": {
        "log_file_created": "2026-07-13T06:06:25Z"
      }
    },
    {
      "description": "Referred to committee",
      "date": "2025-06-18T04:00:00+00:00",
      "organization_id": "~{\"classification\": \"lower\"}",
      "classification": [
        "referral-committee"
      ],
      "related_entities": [
        {
          "name": "House General Government Committee",
          "entity_type": "organization",
          "organization_id": null
        }
      ],
      "_processing": {
        "log_file_created": "2026-07-13T06:06:25Z"
      }
    }
  ],
  "sponsorships": [
    {
      "name": "Joseph A. Miller, III",
      "classification": "primary",
      "entity_type": "person",
      "primary": true,
      "person_id": "~{\"name\": \"Joseph A. Miller, III\"}",
      "organization_id": null
    },
    {
      "name": "Munira Abdullahi",
      "classification": "primary",
      "entity_type": "person",
      "primary": true,
      "person_id": "~{\"name\": \"Munira Abdullahi\"}",
      "organization_id": null
    },
    {
      "name": "Sean P. Brennan",
      "classification": "cosponsor",
      "entity_type": "person",
      "primary": false,
      "person_id": "~{\"name\": \"Sean P. Brennan\"}",
      "organization_id": null
    },
    {
      "name": "Juanita O. Brent",
      "classification": "cosponsor",
      "entity_type": "person",
      "primary": false,
      "person_id": "~{\"name\": \"Juanita O. Brent\"}",
      "organization_id": null
    },
    {
      "name": "Michele Grim",
      "classification": "cosponsor",
      "entity_type": "person",
      "primary": false,
      "person_id": "~{\"name\": \"Michele Grim\"}",
      "organization_id": null
    },
    {
      "name": "Lauren McNally",
      "classification": "cosponsor",
      "entity_type": "person",
      "primary": false,
      "person_id": "~{\"name\": \"Lauren McNally\"}",
      "organization_id": null
    },
    {
      "name": "Tristan Rader",
      "classification": "cosponsor",
      "entity_type": "person",
      "primary": false,
      "person_id": "~{\"name\": \"Tristan Rader\"}",
      "organization_id": null
    },
    {
      "name": "C. Allison Russo",
      "classification": "cosponsor",
      "entity_type": "person",
      "primary": false,
      "person_id": "~{\"name\": \"C. Allison Russo\"}",
      "organization_id": null
    },
    {
      "name": "Daniel P. Troy",
      "classification": "cosponsor",
      "entity_type": "person",
      "primary": false,
      "person_id": "~{\"name\": \"Daniel P. Troy\"}",
      "organization_id": null
    },
    {
      "name": "Erika White",
      "classification": "cosponsor",
      "entity_type": "person",
      "primary": false,
      "person_id": "~{\"name\": \"Erika White\"}",
      "organization_id": null
    }
  ],
  "related_bills": [],
  "versions": [
    {
      "note": "As Introduced",
      "links": [
        {
          "url": "https://search-prod.lis.state.oh.us/api/v2/general_assembly_136/legislation/hb362/00_IN/pdf/",
          "media_type": "application/pdf"
        },
        {
          "url": "https://search-prod.lis.state.oh.us/api/v2/general_assembly_136/legislation/hb362/00_IN/html/",
          "media_type": "text/html"
        }
      ],
      "date": "",
      "classification": ""
    }
  ],
  "documents": [],
  "citations": [],
  "sources": [
    {
      "url": "https://www.legislature.ohio.gov/legislation/136/hb362",
      "note": ""
    },
    {
      "url": "https://search-prod.lis.state.oh.us/api/v2/general_assembly_136/legislation/hb362/",
      "note": ""
    }
  ],
  "extras": {},
  "jurisdiction": {
    "id": "ocd-jurisdiction/country:us/state:oh/government",
    "name": "Ohio",
    "classification": "state",
    "division_id": "ocd-division/country:us/state:oh"
  },
  "_processing": {
    "logs_latest_update": "2026-07-13T06:06:25Z"
  }
}