{
  "legislative_session": "136",
  "identifier": "HB 696",
  "title": "Modify jurisdiction of the Erie County prosecuting attorney",
  "from_organization": "~{\"classification\": \"lower\"}",
  "classification": [
    "bill"
  ],
  "subject": [
    "Courts",
    "Courts and Civil Law",
    "Crime and Punishment",
    "Crimes, Corrections, and Law Enforcement"
  ],
  "abstracts": [
    {
      "note": "long title",
      "abstract": "To amend section 1901.34 of the Revised Code to modify jurisdiction of the Erie County prosecuting attorney."
    }
  ],
  "other_titles": [
    {
      "note": "long title",
      "title": "To amend section 1901.34 of the Revised Code to modify jurisdiction of the Erie County prosecuting attorney."
    }
  ],
  "other_identifiers": [
    {
      "identifier": "ocd-bill-oh-136-hb696"
    }
  ],
  "actions": [
    {
      "description": "Introduced",
      "date": "2026-02-12T05:00:00+00:00",
      "organization_id": "~{\"classification\": \"lower\"}",
      "classification": [
        "introduction"
      ],
      "related_entities": [],
      "_processing": {
        "log_file_created": "2026-07-14T12:59:50Z"
      }
    },
    {
      "description": "Referred to committee",
      "date": "2026-02-18T05:00:00+00:00",
      "organization_id": "~{\"classification\": \"lower\"}",
      "classification": [
        "referral-committee"
      ],
      "related_entities": [
        {
          "name": "House Judiciary Committee",
          "entity_type": "organization",
          "organization_id": null
        }
      ],
      "_processing": {
        "log_file_created": "2026-07-14T12:59:50Z"
      }
    }
  ],
  "sponsorships": [
    {
      "name": "D. J. Swearingen",
      "classification": "primary",
      "entity_type": "person",
      "primary": true,
      "person_id": "~{\"name\": \"D. J. Swearingen\"}",
      "organization_id": null
    }
  ],
  "related_bills": [],
  "versions": [
    {
      "note": "As Introduced",
      "links": [
        {
          "url": "https://search-prod.lis.state.oh.us/api/v2/general_assembly_136/legislation/hb696/00_IN/pdf/",
          "media_type": "application/pdf"
        },
        {
          "url": "https://search-prod.lis.state.oh.us/api/v2/general_assembly_136/legislation/hb696/00_IN/html/",
          "media_type": "text/html"
        }
      ],
      "date": "",
      "classification": ""
    }
  ],
  "documents": [
    {
      "note": "Analysis: As Introduced",
      "links": [
        {
          "url": "https://www.legislature.ohio.gov//download?key=27162",
          "media_type": "application/pdf"
        }
      ],
      "date": "",
      "classification": ""
    },
    {
      "note": "Fiscal Notes: As Introduced",
      "links": [
        {
          "url": "https://www.legislature.ohio.gov//download?key=27281",
          "media_type": "application/pdf"
        }
      ],
      "date": "",
      "classification": ""
    }
  ],
  "citations": [],
  "sources": [
    {
      "url": "https://www.legislature.ohio.gov/legislation/136/hb696",
      "note": ""
    },
    {
      "url": "https://search-prod.lis.state.oh.us/api/v2/general_assembly_136/legislation/hb696/",
      "note": ""
    }
  ],
  "extras": {},
  "jurisdiction": {
    "id": "ocd-jurisdiction/country:us/state:oh/government",
    "name": "Ohio",
    "classification": "state",
    "division_id": "ocd-division/country:us/state:oh"
  },
  "_processing": {
    "logs_latest_update": "2026-07-14T12:59:50Z",
    "text_extraction_latest_update": "2026-07-14T21:13:23.679475Z"
  }
}