{
  "legislative_session": "136",
  "identifier": "HB 638",
  "title": "Designate President Donald Trump Freedom Highway",
  "from_organization": "~{\"classification\": \"lower\"}",
  "classification": [
    "bill"
  ],
  "subject": [
    "Highways, Roads, and Bridges",
    "Memorial Highways and Bridges",
    "Special Designations",
    "Transportation"
  ],
  "abstracts": [
    {
      "note": "long title",
      "abstract": "To enact section 5534.59 of the Revised Code to designate a portion of I-70 in Franklin County as the \"President Donald Trump Freedom Highway.\""
    }
  ],
  "other_titles": [
    {
      "note": "long title",
      "title": "To enact section 5534.59 of the Revised Code to designate a portion of I-70 in Franklin County as the \"President Donald Trump Freedom Highway.\""
    }
  ],
  "other_identifiers": [
    {
      "identifier": "ocd-bill-oh-136-hb638"
    }
  ],
  "actions": [
    {
      "description": "Introduced",
      "date": "2025-12-23T05:00:00+00:00",
      "organization_id": "~{\"classification\": \"lower\"}",
      "classification": [
        "introduction"
      ],
      "related_entities": [],
      "_processing": {
        "log_file_created": "2026-07-14T12:59:50Z"
      }
    },
    {
      "description": "Referred to committee",
      "date": "2026-02-04T05:00:00+00:00",
      "organization_id": "~{\"classification\": \"lower\"}",
      "classification": [
        "referral-committee"
      ],
      "related_entities": [
        {
          "name": "House Transportation Committee",
          "entity_type": "organization",
          "organization_id": null
        }
      ],
      "_processing": {
        "log_file_created": "2026-07-14T12:59:50Z"
      }
    }
  ],
  "sponsorships": [
    {
      "name": "D. J. Swearingen",
      "classification": "primary",
      "entity_type": "person",
      "primary": true,
      "person_id": "~{\"name\": \"D. J. Swearingen\"}",
      "organization_id": null
    },
    {
      "name": "Jeff LaRe",
      "classification": "primary",
      "entity_type": "person",
      "primary": true,
      "person_id": "~{\"name\": \"Jeff LaRe\"}",
      "organization_id": null
    }
  ],
  "related_bills": [],
  "versions": [
    {
      "note": "As Introduced",
      "links": [
        {
          "url": "https://search-prod.lis.state.oh.us/api/v2/general_assembly_136/legislation/hb638/00_IN/pdf/",
          "media_type": "application/pdf"
        },
        {
          "url": "https://search-prod.lis.state.oh.us/api/v2/general_assembly_136/legislation/hb638/00_IN/html/",
          "media_type": "text/html"
        }
      ],
      "date": "",
      "classification": ""
    }
  ],
  "documents": [
    {
      "note": "Analysis: As Introduced",
      "links": [
        {
          "url": "https://www.legislature.ohio.gov//download?key=26915",
          "media_type": "application/pdf"
        }
      ],
      "date": "",
      "classification": ""
    },
    {
      "note": "Fiscal Notes: As Introduced",
      "links": [
        {
          "url": "https://www.legislature.ohio.gov//download?key=27772",
          "media_type": "application/pdf"
        }
      ],
      "date": "",
      "classification": ""
    }
  ],
  "citations": [],
  "sources": [
    {
      "url": "https://www.legislature.ohio.gov/legislation/136/hb638",
      "note": ""
    },
    {
      "url": "https://search-prod.lis.state.oh.us/api/v2/general_assembly_136/legislation/hb638/",
      "note": ""
    }
  ],
  "extras": {},
  "jurisdiction": {
    "id": "ocd-jurisdiction/country:us/state:oh/government",
    "name": "Ohio",
    "classification": "state",
    "division_id": "ocd-division/country:us/state:oh"
  },
  "_processing": {
    "logs_latest_update": "2026-07-14T12:59:50Z"
  }
}