{
  "legislative_session": "136",
  "identifier": "HB 955",
  "title": "Expand homestead exemption - disabled veteran\u2019s surviving spouse",
  "from_organization": "~{\"classification\": \"lower\"}",
  "classification": [
    "bill"
  ],
  "subject": [
    "Housing and Real Property",
    "Military and Veterans",
    "Taxation"
  ],
  "abstracts": [
    {
      "note": "long title",
      "abstract": "To amend sections 323.151, 323.152, 4503.064, and 4503.065 of the Revised Code to expand the enhanced homestead exemption for the surviving spouse of a disabled veteran."
    }
  ],
  "other_titles": [
    {
      "note": "long title",
      "title": "To amend sections 323.151, 323.152, 4503.064, and 4503.065 of the Revised Code to expand the enhanced homestead exemption for the surviving spouse of a disabled veteran."
    }
  ],
  "other_identifiers": [
    {
      "identifier": "ocd-bill-oh-136-hb955"
    }
  ],
  "actions": [
    {
      "description": "Introduced",
      "date": "2026-05-27T04:00:00+00:00",
      "organization_id": "~{\"classification\": \"lower\"}",
      "classification": [
        "introduction"
      ],
      "related_entities": [],
      "_processing": {
        "log_file_created": "2026-07-14T12:59:50Z"
      }
    },
    {
      "description": "Referred to committee",
      "date": "2026-06-03T04:00:00+00:00",
      "organization_id": "~{\"classification\": \"lower\"}",
      "classification": [
        "referral-committee"
      ],
      "related_entities": [
        {
          "name": "House Ways and Means Committee",
          "entity_type": "organization",
          "organization_id": null
        }
      ],
      "_processing": {
        "log_file_created": "2026-07-14T12:59:50Z"
      }
    }
  ],
  "sponsorships": [
    {
      "name": "Joseph A. Miller, III",
      "classification": "primary",
      "entity_type": "person",
      "primary": true,
      "person_id": "~{\"name\": \"Joseph A. Miller, III\"}",
      "organization_id": null
    },
    {
      "name": "Chris Glassburn",
      "classification": "primary",
      "entity_type": "person",
      "primary": true,
      "person_id": "~{\"name\": \"Chris Glassburn\"}",
      "organization_id": null
    }
  ],
  "related_bills": [],
  "versions": [
    {
      "note": "As Introduced",
      "links": [
        {
          "url": "https://search-prod.lis.state.oh.us/api/v2/general_assembly_136/legislation/hb955/00_IN/pdf/",
          "media_type": "application/pdf"
        },
        {
          "url": "https://search-prod.lis.state.oh.us/api/v2/general_assembly_136/legislation/hb955/00_IN/html/",
          "media_type": "text/html"
        }
      ],
      "date": "",
      "classification": ""
    }
  ],
  "documents": [],
  "citations": [],
  "sources": [
    {
      "url": "https://www.legislature.ohio.gov/legislation/136/hb955",
      "note": ""
    },
    {
      "url": "https://search-prod.lis.state.oh.us/api/v2/general_assembly_136/legislation/hb955/",
      "note": ""
    }
  ],
  "extras": {},
  "jurisdiction": {
    "id": "ocd-jurisdiction/country:us/state:oh/government",
    "name": "Ohio",
    "classification": "state",
    "division_id": "ocd-division/country:us/state:oh"
  },
  "_processing": {
    "logs_latest_update": "2026-07-14T12:59:50Z",
    "text_extraction_latest_update": "2026-07-14T21:19:00.744874Z"
  }
}